VectorsPY.py
VectorsPY-1.0.2.dist-info/LICENSE.txt
VectorsPY-1.0.2.dist-info/METADATA
VectorsPY-1.0.2.dist-info/WHEEL
VectorsPY-1.0.2.dist-info/top_level.txt
VectorsPY-1.0.2.dist-info/RECORD
