Metadata-Version: 2.1
Name: VectorsPY
Version: 1.0.2
Summary: Python Module to allow the use of Vectors
Home-page: https://github.com/aryansh-1/VectorsPY
Author: Aryansh Gupta
Author-email: Aryanshappmaker@gmail.com
License: UNKNOWN
Platform: UNKNOWN
Requires-Python: >=3.1
